kimi_sdk/__init__.py
kimi_sdk/py.typed
kimi_sdk-0.2.1.dist-info/WHEEL
kimi_sdk-0.2.1.dist-info/METADATA
kimi_sdk-0.2.1.dist-info/RECORD
