Metadata-Version: 2.3
Name: kimi-sdk
Version: 0.2.1
Summary: A lightweight Python SDK for the Kimi API.
Requires-Dist: kosong>=0.37.0
Requires-Python: >=3.12
